maleo/infra/__init__.py
maleo/infra/config.example.yaml
maleo/infra/config.py
maleo/infra/heartbeat/__init__.py
maleo/infra/heartbeat/config.example.yaml
maleo/infra/heartbeat/config.py
maleo/infra/heartbeat/monitor.py
maleo/infra/heartbeat/schemas.py
maleo/infra/request/__init__.py
maleo/infra/request/enums.py
maleo/infra/request/monitor.py
maleo/infra/request/schemas.py
maleo/infra/resource/__init__.py
maleo/infra/resource/config.example.yaml
maleo/infra/resource/config.py
maleo/infra/resource/constants.py
maleo/infra/resource/enums.py
maleo/infra/resource/monitor.py
maleo/infra/resource/schemas.py
maleo/infra/resource/utils.py
maleo_infra-0.7.50.dist-info/licenses/LICENSE
maleo_infra-0.7.50.dist-info/METADATA
maleo_infra-0.7.50.dist-info/WHEEL
maleo_infra-0.7.50.dist-info/top_level.txt
maleo_infra-0.7.50.dist-info/RECORD
