Metadata-Version: 2.4
Name: maleo-infra
Version: 0.7.50
Summary: Infra package for MaleoSuite
Author-email: Agra Bima Yuda <agra@nexmedis.com>
License: Proprietary
Requires-Python: >=3.12
License-File: LICENSE
Requires-Dist: annotated-types>=0.7.0
Requires-Dist: anyio>=4.10.0
Requires-Dist: bcrypt>=4.3.0
Requires-Dist: black>=25.1.0
Requires-Dist: cachetools>=5.5.2
Requires-Dist: certifi>=2025.8.3
Requires-Dist: cffi>=2.0.0
Requires-Dist: cfgv>=3.4.0
Requires-Dist: charset-normalizer>=3.4.3
Requires-Dist: click>=8.3.0
Requires-Dist: colorama>=0.4.6
Requires-Dist: cryptography>=46.0.1
Requires-Dist: distlib>=0.4.0
Requires-Dist: fastapi>=0.116.2
Requires-Dist: filelock>=3.19.1
Requires-Dist: google-api-core>=2.25.1
Requires-Dist: google-auth>=2.40.3
Requires-Dist: google-cloud-appengine-logging>=1.6.2
Requires-Dist: google-cloud-audit-log>=0.3.2
Requires-Dist: google-cloud-core>=2.4.3
Requires-Dist: google-cloud-logging>=3.12.1
Requires-Dist: google-cloud-pubsub>=2.31.1
Requires-Dist: googleapis-common-protos>=1.70.0
Requires-Dist: greenlet>=3.2.4
Requires-Dist: grpc-google-iam-v1>=0.14.2
Requires-Dist: grpcio>=1.75.0
Requires-Dist: grpcio-status>=1.75.0
Requires-Dist: h11>=0.16.0
Requires-Dist: httpcore>=1.0.9
Requires-Dist: httpx>=0.28.1
Requires-Dist: identify>=2.6.14
Requires-Dist: idna>=3.10
Requires-Dist: importlib_metadata>=8.7.0
Requires-Dist: iniconfig>=2.1.0
Requires-Dist: maleo-crypto>=0.0.50
Requires-Dist: maleo-enums>=0.0.50
Requires-Dist: maleo-logging>=0.0.50
Requires-Dist: maleo-schemas>=0.7.50
Requires-Dist: maleo-types>=0.0.50
Requires-Dist: maleo-utils>=0.0.50
Requires-Dist: mypy_extensions>=1.1.0
Requires-Dist: nodeenv>=1.9.1
Requires-Dist: opentelemetry-api>=1.37.0
Requires-Dist: opentelemetry-sdk>=1.37.0
Requires-Dist: opentelemetry-semantic-conventions>=0.58b0
Requires-Dist: packaging>=25.0
Requires-Dist: pathspec>=0.12.1
Requires-Dist: platformdirs>=4.4.0
Requires-Dist: pluggy>=1.6.0
Requires-Dist: pre_commit>=4.3.0
Requires-Dist: proto-plus>=1.26.1
Requires-Dist: protobuf>=6.32.1
Requires-Dist: psutil>=7.1.0
Requires-Dist: pyasn1>=0.6.1
Requires-Dist: pyasn1_modules>=0.4.2
Requires-Dist: pycparser>=2.23
Requires-Dist: pycryptodome>=3.23.0
Requires-Dist: pydantic>=2.12.2
Requires-Dist: pydantic-settings>=2.10.1
Requires-Dist: pydantic_core>=2.41.4
Requires-Dist: Pygments>=2.19.2
Requires-Dist: PyJWT>=2.10.1
Requires-Dist: pytest>=8.4.2
Requires-Dist: python-dotenv>=1.1.1
Requires-Dist: pytokens>=0.1.10
Requires-Dist: PyYAML>=6.0.2
Requires-Dist: requests>=2.32.5
Requires-Dist: rsa>=4.9.1
Requires-Dist: sniffio>=1.3.1
Requires-Dist: SQLAlchemy>=2.0.44
Requires-Dist: starlette>=0.48.0
Requires-Dist: typing-inspection>=0.4.2
Requires-Dist: typing_extensions>=4.15.0
Requires-Dist: ua-parser>=1.0.1
Requires-Dist: ua-parser-builtins>=0.18.0.post1
Requires-Dist: urllib3>=2.5.0
Requires-Dist: user-agents>=2.2.0
Requires-Dist: virtualenv>=20.34.0
Requires-Dist: zipp>=3.23.0
Dynamic: license-file
